lyra2re2_hash.cp38-win_amd64.pyd
lyra2re2_hash.pypy38-pp73-win_amd64.pyd
lyra2re3_hash.cp38-win_amd64.pyd
lyra2re3_hash.pypy38-pp73-win_amd64.pyd
lyra2re_hash.cp38-win_amd64.pyd
lyra2re_hash.pypy38-pp73-win_amd64.pyd
verthash.cp38-win_amd64.pyd
verthash.pypy38-pp73-win_amd64.pyd
vtc_scrypt_new.cp38-win_amd64.pyd
vtc_scrypt_new.pypy38-pp73-win_amd64.pyd
vertcoinhash-1.0.1.dist-info/LICENSE
vertcoinhash-1.0.1.dist-info/METADATA
vertcoinhash-1.0.1.dist-info/WHEEL
vertcoinhash-1.0.1.dist-info/top_level.txt
vertcoinhash-1.0.1.dist-info/RECORD
