Metadata-Version: 2.1
Name: vertcoinhash
Version: 1.0.1
Summary: Bindings for proof of work used by Vertcoin
Home-page: https://github.com/vertcoin-project/vertcoinhash-python
Author: vertion
Author-email: vertion@protonmail.com
License: UNKNOWN
Platform: UNKNOWN
License-File: LICENSE
